Workbook

Sheet Executive Summary
B2: FMCG Sector Margin Compression Model (2019-2024)
B3: Professional Commercial Analyst Portfolio Deliverable
B4: Author: Rai Abdul Rehman | Date: May 2026 | Focus: Peak Inflation Strategic Response
B6: Executive Briefing & Strategic Insights
B8: 1. SEVERE MARGIN COMPRESSION DRIVEN BY COGS PRESSURE The Pakistani FMCG sector witnessed unprecedented cost pressure between 2019 and 2024. Average COGS rose from 73.8% in 2019 to a peak of 76.1% in 2022, directly eroding the sector average GPM from 26.2% to a low of 23.9% in 2022. This severe compression was driven by macro-economic shocks, historic PKR devaluation, and supply chain disruptions. Importantly, 2023 saw a dramatic pricing power recovery (GPM spiked to 29.0%) as firms aggressive in price hikes lagged commodity stabilization, before normalizing back to a 26.0% baseline in 2024.
B13: 2. STRATEGIC DIVERGENCE IN MARKETING RESPONSE (PROACTIVE VS. COMMODITY-DEFENSIVE) FMCG firms demonstrated highly divergent strategies to survive cost inflation. Shield Corporation Limited adopted an extremely proactive brand equity defense strategy, maintaining a sector-highest average Advertising-to-Sales (A/S) ratio of 11.6% (exceeding the sector average of 3.77% by 3x) to preserve top-of-mind recall, achieving a resilient average GPM of 26.5%. Conversely, Unity Foods Limited followed a classic commodity-defensive model, spending a razor-thin 0.29% on advertising, which left them exposed with an average GPM of only 9.55% as they operated a high-volume, low-margin business.
B18: 3. THE EMPIRICAL 'MISSING LINK': STRATEGY DOMINATES INFLATION A key value-add of this analysis is the validation of the academic marketing theory under crisis conditions. Contrary to intuitive expectation that high inflation forces sector-wide advertising cuts, empirical regression on this 90-observation dataset proved no statistically significant relationship between inflation (CPI) and advertising-to-sales ratios (empirical β = -0.110, p > .10). This confirms that FMCG advertising spend is not macro-driven, but rather dictated by independent, firm-level strategic choices (brand builder vs. volume vendor) and capital structure constraints.
B23: Strategic Outlier Spotlight (Company Comparison Table)
B25: Comparative Entity | C25: Avg Gross Profit Margin (GPM) | D25: Avg Advertising-to-Sales (A/S) | E25: Avg COGS Ratio | F25: Strategic Classification
B26: Sector Average (15 Companies) | C26: =AVERAGE('Data Input'!H2:H91) | D26: =AVERAGE('Data Input'!J2:J91) | E26: =AVERAGE('Data Input'!I2:I91) | F26: Sector Benchmark
B27: Shield Corporation Limited | C27: =AVERAGEIFS('Data Input'!H2:H91, 'Data Input'!A2:A91, "shield_corporation_limited") | D27: =AVERAGEIFS('Data Input'!J2:J91, 'Data Input'!A2:A91, "shield_corporation_limited") | E27: =AVERAGEIFS('Data Input'!I2:I91, 'Data Input'!A2:A91, "shield_corporation_limited") | F27: Proactive Brand Builder
B28: Unity Foods Limited | C28: =AVERAGEIFS('Data Input'!H2:H91, 'Data Input'!A2:A91, "unity_foods_limited") | D28: =AVERAGEIFS('Data Input'!J2:J91, 'Data Input'!A2:A91, "unity_foods_limited") | E28: =AVERAGEIFS('Data Input'!I2:I91, 'Data Input'!A2:A91, "unity_foods_limited") | F28: Commodity Cost-Leader
B30: Model Specifications & Data Scope
B32: 15 | E32: 6 Years | H32: 90
B34: Firms Analyzed | E34: Time Horizon (2019-2024) | H34: Total Observations

Sheet Summary Dashboard
B2: Sector Margin Compression Timeline (2019-2024)
B4: Year | C4: Total Revenue (PKR) | D4: Total COGS (PKR) | E4: Gross Profit (PKR) | F4: Avg GPM | G4: Avg COGS Ratio | H4: Avg A/S Ratio
B5: 2019 | C5: =SUMIFS('Data Input'!C:C, 'Data Input'!B:B, 2019) | D5: =SUMIFS('Data Input'!D:D, 'Data Input'!B:B, 2019) | E5: =C5-D5 | F5: =AVERAGEIFS('Data Input'!H:H, 'Data Input'!B:B, 2019) | G5: =AVERAGEIFS('Data Input'!I:I, 'Data Input'!B:B, 2019) | H5: =AVERAGEIFS('Data Input'!J:J, 'Data Input'!B:B, 2019)
B6: 2020 | C6: =SUMIFS('Data Input'!C:C, 'Data Input'!B:B, 2020) | D6: =SUMIFS('Data Input'!D:D, 'Data Input'!B:B, 2020) | E6: =C6-D6 | F6: =AVERAGEIFS('Data Input'!H:H, 'Data Input'!B:B, 2020) | G6: =AVERAGEIFS('Data Input'!I:I, 'Data Input'!B:B, 2020) | H6: =AVERAGEIFS('Data Input'!J:J, 'Data Input'!B:B, 2020)
B7: 2021 | C7: =SUMIFS('Data Input'!C:C, 'Data Input'!B:B, 2021) | D7: =SUMIFS('Data Input'!D:D, 'Data Input'!B:B, 2021) | E7: =C7-D7 | F7: =AVERAGEIFS('Data Input'!H:H, 'Data Input'!B:B, 2021) | G7: =AVERAGEIFS('Data Input'!I:I, 'Data Input'!B:B, 2021) | H7: =AVERAGEIFS('Data Input'!J:J, 'Data Input'!B:B, 2021)
B8: 2022 | C8: =SUMIFS('Data Input'!C:C, 'Data Input'!B:B, 2022) | D8: =SUMIFS('Data Input'!D:D, 'Data Input'!B:B, 2022) | E8: =C8-D8 | F8: =AVERAGEIFS('Data Input'!H:H, 'Data Input'!B:B, 2022) | G8: =AVERAGEIFS('Data Input'!I:I, 'Data Input'!B:B, 2022) | H8: =AVERAGEIFS('Data Input'!J:J, 'Data Input'!B:B, 2022)
B9: 2023 | C9: =SUMIFS('Data Input'!C:C, 'Data Input'!B:B, 2023) | D9: =SUMIFS('Data Input'!D:D, 'Data Input'!B:B, 2023) | E9: =C9-D9 | F9: =AVERAGEIFS('Data Input'!H:H, 'Data Input'!B:B, 2023) | G9: =AVERAGEIFS('Data Input'!I:I, 'Data Input'!B:B, 2023) | H9: =AVERAGEIFS('Data Input'!J:J, 'Data Input'!B:B, 2023)
B10: 2024 | C10: =SUMIFS('Data Input'!C:C, 'Data Input'!B:B, 2024) | D10: =SUMIFS('Data Input'!D:D, 'Data Input'!B:B, 2024) | E10: =C10-D10 | F10: =AVERAGEIFS('Data Input'!H:H, 'Data Input'!B:B, 2024) | G10: =AVERAGEIFS('Data Input'!I:I, 'Data Input'!B:B, 2024) | H10: =AVERAGEIFS('Data Input'!J:J, 'Data Input'!B:B, 2024)
B11: Sector Mean | C11: =AVERAGE(C5:C10) | D11: =AVERAGE(D5:D10) | E11: =AVERAGE(E5:E10) | F11: =AVERAGE(F5:F10) | G11: =AVERAGE(G5:G10) | H11: =AVERAGE(H5:H10)

Sheet Scenario Analysis
B2: Sensitivity Analysis: Contribution Margin After Marketing (CMAM)
B4: Baseline Metrics (Sector Averages)
B5: Sector Average Gross Profit Margin (GPM): | D5: =AVERAGE('Data Input'!H2:H91)
B6: Sector Average Advertising-to-Sales (A/S) Ratio: | D6: =AVERAGE('Data Input'!J2:J91)
B7: Baseline Contribution Margin After Marketing (CMAM): | D7: =D5-D6
B9: Advertising Budget Sensitivity Matrix (Static Revenue)
B11: Scenario | C11: Change in Advertising | D11: Ad-to-Sales Ratio | E11: Model GPM | F11: CMAM | G11: Variance from Baseline (bps)
B12: Extreme Budget Cut | C12: -0.3 | D12: =$D$6*(1+C12) | E12: =$D$5 | F12: =E12-D12 | G12: =(F12-$D$7)*10000
B13: Moderate Budget Cut | C13: -0.2 | D13: =$D$6*(1+C13) | E13: =$D$5 | F13: =E13-D13 | G13: =(F13-$D$7)*10000
B14: Mild Budget Cut | C14: -0.1 | D14: =$D$6*(1+C14) | E14: =$D$5 | F14: =E14-D14 | G14: =(F14-$D$7)*10000
B15: Baseline (Current Sector) | C15: 0 | D15: =$D$6*(1+C15) | E15: =$D$5 | F15: =E15-D15 | G15: =(F15-$D$7)*10000
B16: Mild Budget Expansion | C16: 0.1 | D16: =$D$6*(1+C16) | E16: =$D$5 | F16: =E16-D16 | G16: =(F16-$D$7)*10000
B17: Moderate Budget Expansion | C17: 0.2 | D17: =$D$6*(1+C17) | E17: =$D$5 | F17: =E17-D17 | G17: =(F17-$D$7)*10000
B18: Extreme Budget Expansion | C18: 0.3 | D18: =$D$6*(1+C18) | E18: =$D$5 | F18: =E18-D18 | G18: =(F18-$D$7)*10000
B21: Note on Empirical Findings vs. Scenario Modeling: The Scenario Analysis above represents sensitivity modeling based on standard financial planning assumptions (e.g., assessing the linear cost erosion of marketing expenditures on the Contribution Margin After Marketing - CMAM). However, empirical regression analysis conducted on this specific 90-observation dataset reveals that the actual relationship between advertising spend and revenue is not statistically significant (empirical β = -0.110, p > .10), confirming that macro-economic conditions during the peak inflation crisis did not result in a uniform industry-wide advertising-to-sales correlation. In reality, firm-level strategic positioning (such as Shield Corp's brand defense vs. Unity Foods' commodity cost-leadership) dominated macro forces. Therefore, ad budget expansion does not empirically guarantee revenue growth or margin degradation within this market sample.

Sheet COGS Waterfall
B2: Waterfall Analysis: Gross Margin Erosion & Recovery Walk
B4: GPM Progression Step | C4: Base (Invisible) | D4: Erosion (COGS Increase) | E4: Recovery (Pricing Power) | F4: Pillars (Endpoint) | H4: Actual GPM Ref
B5: 2019 GPM (Start) | C5: 0 | D5: 0 | E5: 0 | F5: =H5 | H5: ='Summary Dashboard'!F5
B6: 2020 COGS Pressure | C6: =MIN(H6, H5) | D6: =IF(H6 < H5, H5 - H6, 0) | E6: =IF(H6 > H5, H6 - H5, 0) | F6: 0 | H6: ='Summary Dashboard'!F6
B7: 2021 Margin Recovery | C7: =MIN(H7, H6) | D7: =IF(H7 < H6, H6 - H7, 0) | E7: =IF(H7 > H6, H7 - H6, 0) | F7: 0 | H7: ='Summary Dashboard'!F7
B8: 2022 Peak Inflation COGS | C8: =MIN(H8, H7) | D8: =IF(H8 < H7, H7 - H8, 0) | E8: =IF(H8 > H7, H8 - H7, 0) | F8: 0 | H8: ='Summary Dashboard'!F8
B9: 2023 Pricing Power Spike | C9: =MIN(H9, H8) | D9: =IF(H9 < H8, H8 - H9, 0) | E9: =IF(H9 > H8, H9 - H8, 0) | F9: 0 | H9: ='Summary Dashboard'!F9
B10: 2024 Margin Normalization | C10: =MIN(H10, H9) | D10: =IF(H10 < H9, H9 - H10, 0) | E10: =IF(H10 > H9, H10 - H9, 0) | F10: 0 | H10: ='Summary Dashboard'!F10
B11: 2024 GPM (End) | C11: 0 | D11: 0 | E11: 0 | F11: =H11 | H11: ='Summary Dashboard'!F10

Sheet Data Input
A1: firm_name | B1: year | C1: revenue | D1: cogs | E1: advertising | F1: ebit | G1: finance_costs | H1: gpm | I1: cogs_ratio | J1: as_ratio | K1: icr | L1: cpi | M1: sbp_rate
A2: mitchells_fruit_farms_limited | B2: 2019 | C2: 1987552095 | D2: 1553138999 | E2: 25943230 | F2: 26777465 | G2: 78300349 | H2: 0.2186 | I2: 0.7814 | J2: 0.0131 | K2: 0.342 | L2: 10.578362 | M2: 11.990411
A3: mitchells_fruit_farms_limited | B3: 2020 | C3: 2112492576 | D3: 1670069764 | E3: 12995746 | F3: 47016162 | G3: 74272355 | H3: 0.2094 | I3: 0.7906 | J3: 0.0062 | K3: 0.633 | L3: 9.7399931 | M3: 8.9364754
A4: mitchells_fruit_farms_limited | B4: 2021 | C4: 2210620000 | D4: 1721280000 | E4: 24019000 | F4: 67426000 | G4: 25631000 | H4: 0.2214 | I4: 0.7786 | J4: 0.0109 | K4: 2.6306 | L4: 9.4962106 | M4: 7.2808219
A5: mitchells_fruit_farms_limited | B5: 2022 | C5: 2489291011 | D5: 2295470632 | E5: 179515917 | F5: -597192213 | G5: 36980631 | H5: 0.0779 | I5: 0.9221 | J5: 0.0721 | K5: -16.1488 | L5: 19.87386 | M5: 11.991096
A6: mitchells_fruit_farms_limited | B6: 2023 | C6: 2724930890 | D6: 2076814684 | E6: 33416934 | F6: 15439408 | G6: 85083157 | H6: 0.2379 | I6: 0.7628 | J6: 0.0123 | K6: 0.181 | L6: 30.768128 | M6: 20.613699
A7: mitchells_fruit_farms_limited | B7: 2024 | C7: 2642163811 | D7: 1852996860 | E7: 1902336 | F7: 270527955 | G7: 96186801 | H7: 0.2986 | I7: 0.7013 | J7: 0.0007 | K7: 2.813 | L7: 12.632532 | M7: 18.961749
A8: colgate_palmolive_pakistan_ltd | B8: 2019 | C8: 48718781000 | D8: 26490454000 | E8: 2365195000 | F8: 5002686000 | G8: 38496000 | H8: 0.4563 | I8: 0.5438 | J8: 0.0485 | K8: 129.965 | L8: 10.578362 | M8: 11.990411
A9: colgate_palmolive_pakistan_ltd | B9: 2020 | C9: 43530322000 | D9: 30912914000 | E9: 2278060000 | F9: 6807580000 | G9: 95813000 | H9: 0.2899 | I9: 0.7101 | J9: 0.0523 | K9: 71.049 | L9: 9.7399931 | M9: 8.9364754
A10: colgate_palmolive_pakistan_ltd | B10: 2021 | C10: 67567680000 | D10: 35715642000 | E10: 2821256000 | F10: 8080848000 | G10: 118175000 | H10: 0.4714 | I10: 0.5286 | J10: 0.0418 | K10: 68.379 | L10: 9.4962106 | M10: 7.2808219
A11: colgate_palmolive_pakistan_ltd | B11: 2022 | C11: 62330226000 | D11: 46288481000 | E11: 2632780000 | F11: 8864832000 | G11: 142810000 | H11: 0.2574 | I11: 0.7427 | J11: 0.0422 | K11: 62.074 | L11: 19.87386 | M11: 11.991096
A12: colgate_palmolive_pakistan_ltd | B12: 2023 | C12: 91459504000 | D12: 65360062000 | E12: 3291302000 | F12: 16684618000 | G12: 150682000 | H12: 0.2854 | I12: 0.7146 | J12: 0.036 | K12: 110.7203 | L12: 30.768128 | M12: 20.613699
A13: colgate_palmolive_pakistan_ltd | B13: 2024 | C13: 113230777000 | D13: 76338286000 | E13: 4209973000 | F13: 27799569000 | G13: 165476000 | H13: 0.3258 | I13: 0.6742 | J13: 0.0372 | K13: 168.0937 | L13: 12.632532 | M13: 18.961749
... A91: attahur_limited | B91: 2024 | C91: 5845443000 | D91: 3438553000 | E91: 48964000 | F91: 832359000 | G91: 282540000 | H91: 0.4118 | I91: 0.5882 | J91: 0.0084 | K91: 2.946 | L91: 12.632532 | M91: 18.961749
