Workbook

Sheet 1. INPUT ASSUMPTIONS
B2: ACE Money Transfer - Payment Economics & Corridor Assumptions
B3: Commercial Analyst Portfolio Deliverable | Baseline Remittance Models
B5: Corridor Baseline Parameters
B6: Corridor Parameter | C6: GBP-PKR | D6: USD-PKR | E6: EUR-PKR
B7: Monthly Tx Volume (Audit Average) | C7: 35000 | D7: 10000 | E7: 5000
B8: Average Tx Value (FCY) | C8: 280 | D8: 220 | E8: 190
B9: Flat Remittance Fee (FCY) | C9: 1.5 | D9: 2 | E9: 1.5
B10: Exchange Rate (FCY to GBP) | C10: 1 | D10: 0.8 | E10: 0.85
B11: FX Spread % Quoted to Customer | C11: 0.021 | D11: 0.019 | E11: 0.023
B13: Card Acquirer Fee Tiers
B14: Monthly Volume Tier (tx) | C14: Acquirer Card Fee %
B15: 0 | C15: 0.018
B16: 1001 | C16: 0.015
B17: 5000 | C17: 0.012
B19: Operating & Marketing Cost Parameters
B20: Compliance Cost per Transaction (Fixed) | C20: 0.35
B21: Payout Network Cost per Transaction (Fixed) | C21: 0.28
B22: Failed Transaction Rate | C22: 0.021
B23: Failed Transaction Processing Cost (Penalty) | C23: 0.5
B24: Customer Acquisition Cost (CAC) | C24: 18
B25: Average Customer Retention (Months) | C25: 18
B26: Transactions per Customer per Month | C26: 4
B27: FX Slippage Rate (Leakage Assumption) | C27: 0.0015
B28: Promo Waiver Rate (Marketing Leakage) | C28: 0.003
B29: Monthly Fixed Operations Overhead (GBP) | C29: 25000

Sheet 2. UNIT ECONOMICS
B2: Transaction Unit Economics per Corridor
B4: Unit Metric (GBP / £ equivalent) | C4: GBP-PKR Corridor | D4: USD-PKR Corridor | E4: EUR-PKR Corridor
B5: Average Send Value (GBP Equivalent) | C5: ='1. INPUT ASSUMPTIONS'!C8*'1. INPUT ASSUMPTIONS'!C10 | D5: ='1. INPUT ASSUMPTIONS'!D8*'1. INPUT ASSUMPTIONS'!D10 | E5: ='1. INPUT ASSUMPTIONS'!E8*'1. INPUT ASSUMPTIONS'!E10
B6: Remittance Fee Revenue (GBP) | C6: ='1. INPUT ASSUMPTIONS'!C9*'1. INPUT ASSUMPTIONS'!C10 | D6: ='1. INPUT ASSUMPTIONS'!D9*'1. INPUT ASSUMPTIONS'!D10 | E6: ='1. INPUT ASSUMPTIONS'!E9*'1. INPUT ASSUMPTIONS'!E10
B7: FX Spread Revenue (GBP Quoted) | C7: =C5*'1. INPUT ASSUMPTIONS'!C11 | D7: =D5*'1. INPUT ASSUMPTIONS'!D11 | E7: =E5*'1. INPUT ASSUMPTIONS'!E11
B8: Total Transaction Revenue | C8: =C6+C7 | D8: =D6+D7 | E8: =E6+E7
B9: Acquirer Card Acceptance Fee % | C9: =VLOOKUP('1. INPUT ASSUMPTIONS'!C7,'1. INPUT ASSUMPTIONS'!$B$15:$C$17,2,TRUE) | D9: =VLOOKUP('1. INPUT ASSUMPTIONS'!D7,'1. INPUT ASSUMPTIONS'!$B$15:$C$17,2,TRUE) | E9: =VLOOKUP('1. INPUT ASSUMPTIONS'!E7,'1. INPUT ASSUMPTIONS'!$B$15:$C$17,2,TRUE)
B10: Acquirer Card Acceptance Cost (GBP) | C10: =C5*C9 | D10: =D5*D9 | E10: =E5*E9
B11: Compliance Verification Cost | C11: ='1. INPUT ASSUMPTIONS'!$C$20 | D11: ='1. INPUT ASSUMPTIONS'!$C$20 | E11: ='1. INPUT ASSUMPTIONS'!$C$20
B12: Local Bank Payout Network Cost | C12: ='1. INPUT ASSUMPTIONS'!$C$21 | D12: ='1. INPUT ASSUMPTIONS'!$C$21 | E12: ='1. INPUT ASSUMPTIONS'!$C$21
B13: Failed Transaction Gateways Impact | C13: ='1. INPUT ASSUMPTIONS'!$C$22*'1. INPUT ASSUMPTIONS'!$C$23 | D13: ='1. INPUT ASSUMPTIONS'!$C$22*'1. INPUT ASSUMPTIONS'!$C$23 | E13: ='1. INPUT ASSUMPTIONS'!$C$22*'1. INPUT ASSUMPTIONS'!$C$23
B14: Total Cost per Transaction | C14: =SUM(C10:C13) | D14: =SUM(D10:D13) | E14: =SUM(E10:E13)
B15: Contribution Margin per Transaction (GBP) | C15: =C8-C14 | D15: =D8-D14 | E15: =E8-E14
B16: Contribution Margin % (CM %) | C16: =C15/C8 | D16: =D15/D8 | E16: =E15/E8
B17: Transactions per Customer Lifespan | C17: ='1. INPUT ASSUMPTIONS'!$C$25*'1. INPUT ASSUMPTIONS'!$C$26 | D17: ='1. INPUT ASSUMPTIONS'!$C$25*'1. INPUT ASSUMPTIONS'!$C$26 | E17: ='1. INPUT ASSUMPTIONS'!$C$25*'1. INPUT ASSUMPTIONS'!$C$26
B18: Customer Lifetime Value (LTV based on CM) | C18: =C17*C15 | D18: =D17*D15 | E18: =E17*E15
B19: Customer Acquisition Cost (CAC) | C19: ='1. INPUT ASSUMPTIONS'!$C$24 | D19: ='1. INPUT ASSUMPTIONS'!$C$24 | E19: ='1. INPUT ASSUMPTIONS'!$C$24
B20: LTV to CAC Ratio (Target: >3x) | C20: =C18/C19 | D20: =D18/D19 | E20: =E18/E19
B21: Payback Period (Months) | C21: =C19/(C15*'1. INPUT ASSUMPTIONS'!$C$26) | D21: =D19/(D15*'1. INPUT ASSUMPTIONS'!$C$26) | E21: =E19/(E15*'1. INPUT ASSUMPTIONS'!$C$26)
B22: Monthly Fixed Operating Overhead (GBP) | C22: ='1. INPUT ASSUMPTIONS'!$C$29 | D22: ='1. INPUT ASSUMPTIONS'!$C$29 | E22: ='1. INPUT ASSUMPTIONS'!$C$29
B23: Break-Even Monthly Volume (Transactions) | C23: =C22/C15 | D23: =D22/D15 | E23: =E22/E15

Sheet 3. CORRIDOR BENCHMARKING
B2: Corridor Benchmarking Matrix & Regulatory Stress Test
B4: Benchmark Comparison Metric | C4: GBP-PKR Corridor | D4: USD-PKR Corridor | E4: EUR-PKR Corridor | F4: Corridor Profitability Rank | G4: FX 0.5% Stress Test CM % | H4: Stress CM Variance (bps)
B5: Monthly Transaction Volume | C5: ='1. INPUT ASSUMPTIONS'!C7 | D5: ='1. INPUT ASSUMPTIONS'!D7 | E5: ='1. INPUT ASSUMPTIONS'!E7 | F5: =RANK(C13, $C$13:$E$13, 0) | G5: =(C12-(C6*0.005))/(C7-(C6*0.005)) | H5: =(G5-C13)*10000
B6: Average Send Amount per Remittance | C6: ='2. UNIT ECONOMICS'!C5 | D6: ='2. UNIT ECONOMICS'!D5 | E6: ='2. UNIT ECONOMICS'!E5
B7: Gross Transaction Revenue | C7: ='2. UNIT ECONOMICS'!C8 | D7: ='2. UNIT ECONOMICS'!D8 | E7: ='2. UNIT ECONOMICS'!E8 | F7: =RANK(D13, $C$13:$E$13, 0) | G7: =(D12-(D6*0.005))/(D7-(D6*0.005)) | H7: =(G7-D13)*10000
B8: Acquirer Card Acceptance Fee % | C8: ='2. UNIT ECONOMICS'!C9 | D8: ='2. UNIT ECONOMICS'!D9 | E8: ='2. UNIT ECONOMICS'!E9
B9: Compliance & Verification overhead | C9: ='2. UNIT ECONOMICS'!C11 | D9: ='2. UNIT ECONOMICS'!D11 | E9: ='2. UNIT ECONOMICS'!E11 | F9: =RANK(E13, $C$13:$E$13, 0) | G9: =(E12-(E6*0.005))/(E7-(E6*0.005)) | H9: =(G9-E13)*10000
B10: Payout Network Partner overhead | C10: ='2. UNIT ECONOMICS'!C12 | D10: ='2. UNIT ECONOMICS'!D12 | E10: ='2. UNIT ECONOMICS'!E12
B11: Total Transaction Costs (GBP) | C11: ='2. UNIT ECONOMICS'!C14 | D11: ='2. UNIT ECONOMICS'!D14 | E11: ='2. UNIT ECONOMICS'!E14
B12: Contribution Margin per Transaction | C12: ='2. UNIT ECONOMICS'!C15 | D12: ='2. UNIT ECONOMICS'!D15 | E12: ='2. UNIT ECONOMICS'!E15
B13: Contribution Margin % (CM %) | C13: ='2. UNIT ECONOMICS'!C16 | D13: ='2. UNIT ECONOMICS'!D16 | E13: ='2. UNIT ECONOMICS'!E16
B14: Customer LTV to CAC Leverage Ratio | C14: ='2. UNIT ECONOMICS'!C20 | D14: ='2. UNIT ECONOMICS'!D20 | E14: ='2. UNIT ECONOMICS'!E20
B15: Corridor Break-Even Monthly Volume | C15: ='2. UNIT ECONOMICS'!C23 | D15: ='2. UNIT ECONOMICS'!D23 | E15: ='2. UNIT ECONOMICS'!E23
B17: Senior Analyst Executive Commentary - Key Corridor Insights
B19: Remittance Business Analysis & Key Recommendations: 1. GBP-PKR Corridor Dominance: GBP-PKR is the absolute primary anchor for ACE Money Transfer, accounting for 70% of volume and yielding the highest contribution margin of 45.8% (£3.38 per transaction) driven by the high average transaction size (£280) and 2.1% FX spread. LTV:CAC is an outstanding 13.5x with a fast payback of 1.3 months. 2. EUR-PKR Exposure: EUR-PKR is the weakest corridor (38.6% margin). This is due to its low volume (5,000 tx/month) which keeps it in the 1.5% acquirer card fee tier (versus the 1.2% tier enjoyed by GBP and USD) and a lower average transaction value (€190). Action: Standardize pricing or drive marketing to reach the 5,000+ transaction tier to lower card fees. 3. Regulatory FX Spread Compression Risk: Under a stressed scenario where competitive and regulatory pressure compresses wholesale margins by 0.5%, all corridors suffer margin contraction. EUR-PKR is highly vulnerable, with margins dropping to 27.0% (a -1,159 bps variance), which would severely lengthen its payback period.

Sheet 4. REVENUE LEAKAGE TRACKER
B2: Revenue Leakage & Margin Erosion Tracker (Monthly Aggregate)
B4: Leakage Walk Item | C4: Monthly Value (GBP / £) | D4: % of Gross Revenue | E4: Leakage Status Alert
B5: Gross Remittance Revenue (Fees + FX Spreads) | C5: =SUMPRODUCT('1. INPUT ASSUMPTIONS'!$C$7:$E$7, '2. UNIT ECONOMICS'!$C$8:$E$8) | D5: =C5/C5 | E5: Baseline
B6: FX Slippage Loss (Wholesale Settlement) | C6: =SUMPRODUCT('1. INPUT ASSUMPTIONS'!$C$7:$E$7, '2. UNIT ECONOMICS'!$C$5:$E$5)*'1. INPUT ASSUMPTIONS'!$C$27 | D6: =C6/$C$5 | E6: Leakage
B7: Failed Transaction gateways processing overhead | C7: =('1. INPUT ASSUMPTIONS'!$C$7+'1. INPUT ASSUMPTIONS'!$D$7+'1. INPUT ASSUMPTIONS'!$E$7)*'1. INPUT ASSUMPTIONS'!$C$22*'1. INPUT ASSUMPTIONS'!$C$23 | D7: =C7/$C$5 | E7: Leakage
B8: Promotional Waivers & Customer Incentives | C8: =SUMPRODUCT('1. INPUT ASSUMPTIONS'!$C$7:$E$7, '2. UNIT ECONOMICS'!$C$5:$E$5)*'1. INPUT ASSUMPTIONS'!$C$28 | D8: =C8/$C$5 | E8: Leakage
B9: Compliance KYC & Verification Fees | C9: =SUM('1. INPUT ASSUMPTIONS'!$C$7:$E$7)*'1. INPUT ASSUMPTIONS'!$C$20 | D9: =C9/$C$5 | E9: Cost
B10: Payout Network Partner Fees | C10: =SUM('1. INPUT ASSUMPTIONS'!$C$7:$E$7)*'1. INPUT ASSUMPTIONS'!$C$21 | D10: =C10/$C$5 | E10: Cost
B11: Acquirer Credit Card Processing Costs | C11: =SUMPRODUCT('1. INPUT ASSUMPTIONS'!$C$7:$E$7, '2. UNIT ECONOMICS'!$C$10:$E$10) | D11: =C11/$C$5 | E11: Cost
B12: Net Contribution Margin (Residual Profit) | C12: =C5-SUM(C6:C11) | D12: =C12/C5 | E12: Ending Margin
B15: Revenue Leakage Summary
B16: Total Monthly Operational Revenue Leakage (Slippage + Failed + Promo): | C16: =SUM(C6,C7,C8) | D16: =C16/C5 | E16: =IF(D16>0.08, "HIGH LEAKAGE - ACTION NEEDED", IF(D16>=0.05, "MODERATE LEAKAGE", "HEALTHY LEAKAGE"))

Sheet 5. EXECUTIVE DASHBOARD
B2: ACE Money Transfer - Executive Payments Dashboard
B3: Real-time Operational Performance & Corridor Profitability Overview
B5: ='2. UNIT ECONOMICS'!C16 | E5: ='4. Revenue Leakage Tracker'!D16 | H5: GBP-PKR Corridor | K5: ='4. Revenue Leakage Tracker'!C12
B7: GBP-PKR Anchor Contribution % | E7: Operational Revenue Leakage % | H7: Best Performing Corridor | K7: Monthly Net Contribution (GBP)
B9: Corridor Health & Traffic Light Status
B11: Corridor Route | C11: Monthly Volume (tx) | D11: Average CM % | E11: Regulatory GPM stress test | F11: Health Status
B12: GBP-PKR (Remittance from UK) | C12: ='1. INPUT ASSUMPTIONS'!C7 | D12: ='2. UNIT ECONOMICS'!C16 | E12: ='3. CORRIDOR BENCHMARKING'!G5 | F12: =IF(D12>0.4, "GREEN - RESILIENT", IF(D12>=0.3, "AMBER", "RED"))
B13: USD-PKR (Remittance from US/Global) | C13: ='1. INPUT ASSUMPTIONS'!D7 | D13: ='2. UNIT ECONOMICS'!D16 | E13: ='3. CORRIDOR BENCHMARKING'!G7 | F13: =IF(D13>0.4, "GREEN - RESILIENT", IF(D13>=0.3, "AMBER", "RED"))
B14: EUR-PKR (Remittance from Europe) | C14: ='1. INPUT ASSUMPTIONS'!E7 | D14: ='2. UNIT ECONOMICS'!E16 | E14: ='3. CORRIDOR BENCHMARKING'!G9 | F14: =IF(D14>0.4, "GREEN - RESILIENT", IF(D14>=0.3, "AMBER - COST PRESSURE", "RED"))

Sheet 6. TRANSACTION LOG
A1: Tx ID | B1: Timestamp | C1: Customer ID | D1: Corridor | E1: Currency | F1: Amount (FCY) | G1: Exch Rate | H1: Amount (GBP) | I1: Fee (GBP) | J1: FX Spread % | K1: Status | L1: Slippage (GBP) | M1: Promo Waiver (GBP) | N1: Acquirer Fee (GBP)
A2: ACE-10001 | B2: 2026-05-14 15:44:38 | C2: CUST-80796 | D2: USD-PKR | E2: USD | F2: 230.05053 | G2: 0.8 | H2: 184.04042 | I2: 1.6 | J2: 0.019 | K2: Success | L2: 0.27606063 | M2: 0 | N2: 2.208485
A3: ACE-10002 | B3: 2026-05-23 12:44:55 | C3: CUST-79755 | D3: GBP-PKR | E3: GBP | F3: 274.77791 | G3: 1 | H3: 274.77791 | I3: 1.5 | J3: 0.021 | K3: Success | L3: 0.41216687 | M3: 0 | N3: 3.2973349
A4: ACE-10003 | B4: 2026-05-09 20:50:40 | C4: CUST-88652 | D4: USD-PKR | E4: USD | F4: 233.55005 | G4: 0.8 | H4: 186.84004 | I4: 1.6 | J4: 0.019 | K4: Success | L4: 0.28026006 | M4: 0.56052012 | N4: 2.2420805
A5: ACE-10004 | B5: 2026-05-14 09:34:14 | C5: CUST-92443 | D5: EUR-PKR | E5: EUR | F5: 220.15395 | G5: 0.85 | H5: 187.13085 | I5: 1.275 | J5: 0.023 | K5: Success | L5: 0.28069628 | M5: 0 | N5: 2.8069628
A6: ACE-10005 | B6: 2026-05-05 09:03:10 | C6: CUST-70159 | D6: GBP-PKR | E6: GBP | F6: 272.15568 | G6: 1 | H6: 272.15568 | I6: 1.5 | J6: 0.021 | K6: Success | L6: 0.40823352 | M6: 0.81646705 | N6: 3.2658682
A7: ACE-10006 | B7: 2026-05-10 15:07:29 | C7: CUST-95133 | D7: GBP-PKR | E7: GBP | F7: 272.15613 | G7: 1 | H7: 272.15613 | I7: 1.5 | J7: 0.021 | K7: Success | L7: 0.40823419 | M7: 0 | N7: 3.2658736
A8: ACE-10007 | B8: 2026-05-09 16:34:31 | C8: CUST-78688 | D8: GBP-PKR | E8: GBP | F8: 326.26531 | G8: 1 | H8: 326.26531 | I8: 1.5 | J8: 0.021 | K8: Success | L8: 0.48939796 | M8: 0 | N8: 3.9151837
A9: ACE-10008 | B9: 2026-05-14 19:20:38 | C9: CUST-66408 | D9: USD-PKR | E9: USD | F9: 236.36353 | G9: 0.8 | H9: 189.09083 | I9: 1.6 | J9: 0.019 | K9: Success | L9: 0.28363624 | M9: 0 | N9: 2.2690899
A10: ACE-10009 | B10: 2026-05-22 17:37:01 | C10: CUST-94058 | D10: GBP-PKR | E10: GBP | F10: 265.82605 | G10: 1 | H10: 265.82605 | I10: 1.5 | J10: 0.021 | K10: Success | L10: 0.39873908 | M10: 0 | N10: 3.1899127
A11: ACE-10010 | B11: 2026-05-06 15:33:41 | C11: CUST-78981 | D11: GBP-PKR | E11: GBP | F11: 294.13699 | G11: 1 | H11: 294.13699 | I11: 1.5 | J11: 0.021 | K11: Success | L11: 0.44120548 | M11: 0 | N11: 3.5296439
A12: ACE-10011 | B12: 2026-05-19 14:40:52 | C12: CUST-82225 | D12: GBP-PKR | E12: GBP | F12: 265.98711 | G12: 1 | H12: 265.98711 | I12: 1.5 | J12: 0.021 | K12: Success | L12: 0.39898066 | M12: 0 | N12: 3.1918453
A13: ACE-10012 | B13: 2026-05-14 13:20:42 | C13: CUST-56855 | D13: USD-PKR | E13: USD | F13: 208.94155 | G13: 0.8 | H13: 167.15324 | I13: 1.6 | J13: 0.019 | K13: Success | L13: 0.25072987 | M13: 0 | N13: 2.0058389
... A1001: ACE-11000 | B1001: 2026-05-16 16:07:04 | C1001: CUST-65420 | D1001: GBP-PKR | E1001: GBP | F1001: 295.0214 | G1001: 1 | H1001: 295.0214 | I1001: 1.5 | J1001: 0.021 | K1001: Success | L1001: 0.44253209 | M1001: 0 | N1001: 3.5402567
